{"id":"dist\\index.js","dependencies":[{"name":"c:\\Users\\kotka\\Dev\\netlify-test\\package.json","includedInParent":true,"mtime":1532797250159}],"generated":{"js":"var define;\nvar _typeof = typeof Symbol === \"function\" && typeof Symbol.iterator === \"symbol\" ? function (obj) { return typeof obj; } : function (obj) { return obj && typeof Symbol === \"function\" && obj.constructor === Symbol && obj !== Symbol.prototype ? \"symbol\" : typeof obj; };\n\nparcelRequire = function (e, r, n, t) {\n  var i = \"function\" == typeof parcelRequire && parcelRequire,\n      o = \"function\" == typeof require && require;function u(n, t) {\n    if (!r[n]) {\n      if (!e[n]) {\n        var f = \"function\" == typeof parcelRequire && parcelRequire;if (!t && f) return f(n, !0);if (i) return i(n, !0);if (o && \"string\" == typeof n) return o(n);var c = new Error(\"Cannot find module '\" + n + \"'\");throw c.code = \"MODULE_NOT_FOUND\", c;\n      }p.resolve = function (r) {\n        return e[n][1][r] || r;\n      };var l = r[n] = new u.Module(n);e[n][0].call(l.exports, p, l, l.exports, this);\n    }return r[n].exports;function p(e) {\n      return u(p.resolve(e));\n    }\n  }u.isParcelRequire = !0, u.Module = function (e) {\n    this.id = e, this.bundle = u, this.exports = {};\n  }, u.modules = e, u.cache = r, u.parent = i, u.register = function (r, n) {\n    e[r] = [function (e, r) {\n      r.exports = n;\n    }, {}];\n  };for (var f = 0; f < n.length; f++) {\n    u(n[f]);\n  }if (n.length) {\n    var c = u(n[n.length - 1]);\"object\" == (typeof exports === \"undefined\" ? \"undefined\" : _typeof(exports)) && \"undefined\" != typeof module ? module.exports = c : \"function\" == typeof define && define.amd ? define(function () {\n      return c;\n    }) : t && (this[t] = c);\n  }return u;\n}({ \"1tFC\": [function (require, module, exports) {\n    \"use strict\";\n    function e() {\n      console.log(\"Hello World\");\n    }Object.defineProperty(exports, \"__esModule\", { value: !0 }), exports.doStuff = e;\n  }, {}], \"Focm\": [function (require, module, exports) {\n    \"use strict\";\n    var r = require(\"./utils\");(0, r.doStuff)();\n  }, { \"./utils\": \"1tFC\" }] }, {}, [\"Focm\"], null);\n//# sourceMappingURL=/index.map","map":{"mappings":[{"name":"parcelRequire","generated":{"line":4,"column":0},"source":"dist\\index.js","original":{"line":1,"column":0}},{"generated":{"line":4,"column":16},"source":"dist\\index.js","original":{"line":1,"column":14}},{"name":"e","generated":{"line":4,"column":26},"source":"dist\\index.js","original":{"line":1,"column":23}},{"generated":{"line":4,"column":27},"source":"dist\\index.js","original":{"line":1,"column":14}},{"name":"r","generated":{"line":4,"column":29},"source":"dist\\index.js","original":{"line":1,"column":25}},{"generated":{"line":4,"column":30},"source":"dist\\index.js","original":{"line":1,"column":14}},{"name":"n","generated":{"line":4,"column":32},"source":"dist\\index.js","original":{"line":1,"column":27}},{"generated":{"line":4,"column":33},"source":"dist\\index.js","original":{"line":1,"column":14}},{"name":"t","generated":{"line":4,"column":35},"source":"dist\\index.js","original":{"line":1,"column":29}},{"generated":{"line":4,"column":36},"source":"dist\\index.js","original":{"line":1,"column":14}},{"generated":{"line":4,"column":38},"source":"dist\\index.js","original":{"line":1,"column":31}},{"generated":{"line":5,"column":0},"source":"dist\\index.js","original":{"line":1,"column":32}},{"name":"i","generated":{"line":5,"column":6},"source":"dist\\index.js","original":{"line":1,"column":36}},{"generated":{"line":5,"column":10},"source":"dist\\index.js","original":{"line":1,"column":38}},{"generated":{"line":5,"column":24},"source":"dist\\index.js","original":{"line":1,"column":50}},{"name":"parcelRequire","generated":{"line":5,"column":31},"source":"dist\\index.js","original":{"line":1,"column":57}},{"generated":{"line":5,"column":44},"source":"dist\\index.js","original":{"line":1,"column":38}},{"name":"parcelRequire","generated":{"line":5,"column":48},"source":"dist\\index.js","original":{"line":1,"column":72}},{"generated":{"line":5,"column":61},"source":"dist\\index.js","original":{"line":1,"column":32}},{"generated":{"line":6,"column":0},"source":"dist\\index.js","original":{"line":1,"column":32}},{"name":"o","generated":{"line":6,"column":6},"source":"dist\\index.js","original":{"line":1,"column":86}},{"generated":{"line":6,"column":10},"source":"dist\\index.js","original":{"line":1,"column":88}},{"generated":{"line":6,"column":24},"source":"dist\\index.js","original":{"line":1,"column":100}},{"name":"require","generated":{"line":6,"column":31},"source":"dist\\index.js","original":{"line":1,"column":107}},{"generated":{"line":6,"column":38},"source":"dist\\index.js","original":{"line":1,"column":88}},{"name":"require","generated":{"line":6,"column":42},"source":"dist\\index.js","original":{"line":1,"column":116}},{"generated":{"line":6,"column":49},"source":"dist\\index.js","original":{"line":1,"column":32}},{"generated":{"line":6,"column":50},"source":"dist\\index.js","original":{"line":1,"column":124}},{"name":"u","generated":{"line":6,"column":59},"source":"dist\\index.js","original":{"line":1,"column":133}},{"generated":{"line":6,"column":60},"source":"dist\\index.js","original":{"line":1,"column":124}},{"name":"n","generated":{"line":6,"column":61},"source":"dist\\index.js","original":{"line":1,"column":135}},{"generated":{"line":6,"column":62},"source":"dist\\index.js","original":{"line":1,"column":124}},{"name":"t","generated":{"line":6,"column":64},"source":"dist\\index.js","original":{"line":1,"column":137}},{"generated":{"line":6,"column":65},"source":"dist\\index.js","original":{"line":1,"column":124}},{"generated":{"line":6,"column":67},"source":"dist\\index.js","original":{"line":1,"column":139}},{"generated":{"line":7,"column":0},"source":"dist\\index.js","original":{"line":1,"column":140}},{"generated":{"line":7,"column":8},"source":"dist\\index.js","original":{"line":1,"column":143}},{"name":"r","generated":{"line":7,"column":9},"source":"dist\\index.js","original":{"line":1,"column":144}},{"name":"n","generated":{"line":7,"column":11},"source":"dist\\index.js","original":{"line":1,"column":146}},{"generated":{"line":7,"column":12},"source":"dist\\index.js","original":{"line":1,"column":144}},{"generated":{"line":7,"column":13},"source":"dist\\index.js","original":{"line":1,"column":140}},{"generated":{"line":7,"column":15},"source":"dist\\index.js","original":{"line":1,"column":149}},{"generated":{"line":8,"column":0},"source":"dist\\index.js","original":{"line":1,"column":150}},{"generated":{"line":8,"column":10},"source":"dist\\index.js","original":{"line":1,"column":153}},{"name":"e","generated":{"line":8,"column":11},"source":"dist\\index.js","original":{"line":1,"column":154}},{"name":"n","generated":{"line":8,"column":13},"source":"dist\\index.js","original":{"line":1,"column":156}},{"generated":{"line":8,"column":14},"source":"dist\\index.js","original":{"line":1,"column":154}},{"generated":{"line":8,"column":15},"source":"dist\\index.js","original":{"line":1,"column":150}},{"generated":{"line":8,"column":17},"source":"dist\\index.js","original":{"line":1,"column":159}},{"generated":{"line":9,"column":0},"source":"dist\\index.js","original":{"line":1,"column":160}},{"name":"f","generated":{"line":9,"column":12},"source":"dist\\index.js","original":{"line":1,"column":164}},{"generated":{"line":9,"column":16},"source":"dist\\index.js","original":{"line":1,"column":166}},{"generated":{"line":9,"column":30},"source":"dist\\index.js","original":{"line":1,"column":178}},{"name":"parcelRequire","generated":{"line":9,"column":37},"source":"dist\\index.js","original":{"line":1,"column":185}},{"generated":{"line":9,"column":50},"source":"dist\\index.js","original":{"line":1,"column":166}},{"name":"parcelRequire","generated":{"line":9,"column":54},"source":"dist\\index.js","original":{"line":1,"column":200}},{"generated":{"line":9,"column":67},"source":"dist\\index.js","original":{"line":1,"column":160}},{"generated":{"line":9,"column":68},"source":"dist\\index.js","original":{"line":1,"column":214}},{"generated":{"line":9,"column":72},"source":"dist\\index.js","original":{"line":1,"column":217}},{"name":"t","generated":{"line":9,"column":73},"source":"dist\\index.js","original":{"line":1,"column":218}},{"generated":{"line":9,"column":74},"source":"dist\\index.js","original":{"line":1,"column":217}},{"name":"f","generated":{"line":9,"column":78},"source":"dist\\index.js","original":{"line":1,"column":221}},{"generated":{"line":9,"column":79},"source":"dist\\index.js","original":{"line":1,"column":214}},{"generated":{"line":9,"column":81},"source":"dist\\index.js","original":{"line":1,"column":223}},{"name":"f","generated":{"line":9,"column":88},"source":"dist\\index.js","original":{"line":1,"column":230}},{"name":"n","generated":{"line":9,"column":90},"source":"dist\\index.js","original":{"line":1,"column":232}},{"generated":{"line":9,"column":91},"source":"dist\\index.js","original":{"line":1,"column":230}},{"generated":{"line":9,"column":93},"source":"dist\\index.js","original":{"line":1,"column":234}},{"generated":{"line":9,"column":94},"source":"dist\\index.js","original":{"line":1,"column":235}},{"generated":{"line":9,"column":95},"source":"dist\\index.js","original":{"line":1,"column":230}},{"generated":{"line":9,"column":96},"source":"dist\\index.js","original":{"line":1,"column":223}},{"generated":{"line":9,"column":97},"source":"dist\\index.js","original":{"line":1,"column":238}},{"name":"i","generated":{"line":9,"column":101},"source":"dist\\index.js","original":{"line":1,"column":241}},{"generated":{"line":9,"column":102},"source":"dist\\index.js","original":{"line":1,"column":238}},{"generated":{"line":9,"column":104},"source":"dist\\index.js","original":{"line":1,"column":243}},{"name":"i","generated":{"line":9,"column":111},"source":"dist\\index.js","original":{"line":1,"column":250}},{"name":"n","generated":{"line":9,"column":113},"source":"dist\\index.js","original":{"line":1,"column":252}},{"generated":{"line":9,"column":114},"source":"dist\\index.js","original":{"line":1,"column":250}},{"generated":{"line":9,"column":116},"source":"dist\\index.js","original":{"line":1,"column":254}},{"generated":{"line":9,"column":117},"source":"dist\\index.js","original":{"line":1,"column":255}},{"generated":{"line":9,"column":118},"source":"dist\\index.js","original":{"line":1,"column":250}},{"generated":{"line":9,"column":119},"source":"dist\\index.js","original":{"line":1,"column":243}},{"generated":{"line":9,"column":120},"source":"dist\\index.js","original":{"line":1,"column":258}},{"name":"o","generated":{"line":9,"column":124},"source":"dist\\index.js","original":{"line":1,"column":261}},{"generated":{"line":9,"column":129},"source":"dist\\index.js","original":{"line":1,"column":264}},{"generated":{"line":9,"column":141},"source":"dist\\index.js","original":{"line":1,"column":274}},{"name":"n","generated":{"line":9,"column":148},"source":"dist\\index.js","original":{"line":1,"column":281}},{"generated":{"line":9,"column":149},"source":"dist\\index.js","original":{"line":1,"column":258}},{"generated":{"line":9,"column":151},"source":"dist\\index.js","original":{"line":1,"column":283}},{"name":"o","generated":{"line":9,"column":158},"source":"dist\\index.js","original":{"line":1,"column":290}},{"name":"n","generated":{"line":9,"column":160},"source":"dist\\index.js","original":{"line":1,"column":292}},{"generated":{"line":9,"column":161},"source":"dist\\index.js","original":{"line":1,"column":290}},{"generated":{"line":9,"column":162},"source":"dist\\index.js","original":{"line":1,"column":283}},{"generated":{"line":9,"column":163},"source":"dist\\index.js","original":{"line":1,"column":295}},{"name":"c","generated":{"line":9,"column":167},"source":"dist\\index.js","original":{"line":1,"column":299}},{"generated":{"line":9,"column":171},"source":"dist\\index.js","original":{"line":1,"column":301}},{"name":"Error","generated":{"line":9,"column":175},"source":"dist\\index.js","original":{"line":1,"column":305}},{"generated":{"line":9,"column":180},"source":"dist\\index.js","original":{"line":1,"column":301}},{"generated":{"line":9,"column":181},"source":"dist\\index.js","original":{"line":1,"column":311}},{"name":"n","generated":{"line":9,"column":206},"source":"dist\\index.js","original":{"line":1,"column":334}},{"generated":{"line":9,"column":207},"source":"dist\\index.js","original":{"line":1,"column":311}},{"generated":{"line":9,"column":210},"source":"dist\\index.js","original":{"line":1,"column":336}},{"generated":{"line":9,"column":213},"source":"dist\\index.js","original":{"line":1,"column":301}},{"generated":{"line":9,"column":214},"source":"dist\\index.js","original":{"line":1,"column":295}},{"generated":{"line":9,"column":215},"source":"dist\\index.js","original":{"line":1,"column":341}},{"name":"c","generated":{"line":9,"column":221},"source":"dist\\index.js","original":{"line":1,"column":347}},{"name":"code","generated":{"line":9,"column":223},"source":"dist\\index.js","original":{"line":1,"column":349}},{"generated":{"line":9,"column":227},"source":"dist\\index.js","original":{"line":1,"column":347}},{"generated":{"line":9,"column":230},"source":"dist\\index.js","original":{"line":1,"column":354}},{"generated":{"line":9,"column":248},"source":"dist\\index.js","original":{"line":1,"column":347}},{"name":"c","generated":{"line":9,"column":250},"source":"dist\\index.js","original":{"line":1,"column":373}},{"generated":{"line":9,"column":251},"source":"dist\\index.js","original":{"line":1,"column":341}},{"generated":{"line":10,"column":0},"source":"dist\\index.js","original":{"line":1,"column":375}},{"name":"resolve","generated":{"line":10,"column":9},"source":"dist\\index.js","original":{"line":1,"column":377}},{"generated":{"line":10,"column":16},"source":"dist\\index.js","original":{"line":1,"column":375}},{"generated":{"line":10,"column":19},"source":"dist\\index.js","original":{"line":1,"column":385}},{"name":"r","generated":{"line":10,"column":29},"source":"dist\\index.js","original":{"line":1,"column":394}},{"generated":{"line":10,"column":30},"source":"dist\\index.js","original":{"line":1,"column":385}},{"generated":{"line":10,"column":32},"source":"dist\\index.js","original":{"line":1,"column":396}},{"generated":{"line":11,"column":0},"source":"dist\\index.js","original":{"line":1,"column":397}},{"name":"e","generated":{"line":11,"column":15},"source":"dist\\index.js","original":{"line":1,"column":404}},{"name":"n","generated":{"line":11,"column":17},"source":"dist\\index.js","original":{"line":1,"column":406}},{"generated":{"line":11,"column":18},"source":"dist\\index.js","original":{"line":1,"column":404}},{"generated":{"line":11,"column":20},"source":"dist\\index.js","original":{"line":1,"column":409}},{"generated":{"line":11,"column":21},"source":"dist\\index.js","original":{"line":1,"column":404}},{"name":"r","generated":{"line":11,"column":23},"source":"dist\\index.js","original":{"line":1,"column":412}},{"generated":{"line":11,"column":24},"source":"dist\\index.js","original":{"line":1,"column":404}},{"name":"r","generated":{"line":11,"column":29},"source":"dist\\index.js","original":{"line":1,"column":416}},{"generated":{"line":11,"column":30},"source":"dist\\index.js","original":{"line":1,"column":397}},{"generated":{"line":12,"column":0},"source":"dist\\index.js","original":{"line":1,"column":418}},{"generated":{"line":12,"column":7},"source":"dist\\index.js","original":{"line":1,"column":375}},{"generated":{"line":12,"column":8},"source":"dist\\index.js","original":{"line":1,"column":419}},{"name":"l","generated":{"line":12,"column":12},"source":"dist\\index.js","original":{"line":1,"column":423}},{"name":"r","generated":{"line":12,"column":16},"source":"dist\\index.js","original":{"line":1,"column":425}},{"name":"n","generated":{"line":12,"column":18},"source":"dist\\index.js","original":{"line":1,"column":427}},{"generated":{"line":12,"column":19},"source":"dist\\index.js","original":{"line":1,"column":425}},{"generated":{"line":12,"column":23},"source":"dist\\index.js","original":{"line":1,"column":430}},{"name":"u","generated":{"line":12,"column":27},"source":"dist\\index.js","original":{"line":1,"column":434}},{"name":"Module","generated":{"line":12,"column":29},"source":"dist\\index.js","original":{"line":1,"column":436}},{"generated":{"line":12,"column":35},"source":"dist\\index.js","original":{"line":1,"column":430}},{"name":"n","generated":{"line":12,"column":36},"source":"dist\\index.js","original":{"line":1,"column":443}},{"generated":{"line":12,"column":37},"source":"dist\\index.js","original":{"line":1,"column":430}},{"generated":{"line":12,"column":38},"source":"dist\\index.js","original":{"line":1,"column":419}},{"name":"e","generated":{"line":12,"column":39},"source":"dist\\index.js","original":{"line":1,"column":446}},{"name":"n","generated":{"line":12,"column":41},"source":"dist\\index.js","original":{"line":1,"column":448}},{"generated":{"line":12,"column":42},"source":"dist\\index.js","original":{"line":1,"column":446}},{"generated":{"line":12,"column":44},"source":"dist\\index.js","original":{"line":1,"column":451}},{"generated":{"line":12,"column":45},"source":"dist\\index.js","original":{"line":1,"column":446}},{"name":"call","generated":{"line":12,"column":47},"source":"dist\\index.js","original":{"line":1,"column":454}},{"generated":{"line":12,"column":51},"source":"dist\\index.js","original":{"line":1,"column":446}},{"name":"l","generated":{"line":12,"column":52},"source":"dist\\index.js","original":{"line":1,"column":459}},{"name":"exports","generated":{"line":12,"column":54},"source":"dist\\index.js","original":{"line":1,"column":461}},{"generated":{"line":12,"column":61},"source":"dist\\index.js","original":{"line":1,"column":446}},{"name":"p","generated":{"line":12,"column":63},"source":"dist\\index.js","original":{"line":1,"column":469}},{"generated":{"line":12,"column":64},"source":"dist\\index.js","original":{"line":1,"column":446}},{"name":"l","generated":{"line":12,"column":66},"source":"dist\\index.js","original":{"line":1,"column":471}},{"generated":{"line":12,"column":67},"source":"dist\\index.js","original":{"line":1,"column":446}},{"name":"l","generated":{"line":12,"column":69},"source":"dist\\index.js","original":{"line":1,"column":473}},{"name":"exports","generated":{"line":12,"column":71},"source":"dist\\index.js","original":{"line":1,"column":475}},{"generated":{"line":12,"column":78},"source":"dist\\index.js","original":{"line":1,"column":446}},{"generated":{"line":12,"column":80},"source":"dist\\index.js","original":{"line":1,"column":483}},{"generated":{"line":12,"column":84},"source":"dist\\index.js","original":{"line":1,"column":446}},{"generated":{"line":13,"column":0},"source":"dist\\index.js","original":{"line":1,"column":489}},{"name":"r","generated":{"line":13,"column":12},"source":"dist\\index.js","original":{"line":1,"column":496}},{"name":"n","generated":{"line":13,"column":14},"source":"dist\\index.js","original":{"line":1,"column":498}},{"generated":{"line":13,"column":15},"source":"dist\\index.js","original":{"line":1,"column":496}},{"name":"exports","generated":{"line":13,"column":17},"source":"dist\\index.js","original":{"line":1,"column":501}},{"generated":{"line":13,"column":24},"source":"dist\\index.js","original":{"line":1,"column":489}},{"generated":{"line":13,"column":25},"source":"dist\\index.js","original":{"line":1,"column":509}},{"name":"p","generated":{"line":13,"column":34},"source":"dist\\index.js","original":{"line":1,"column":518}},{"generated":{"line":13,"column":35},"source":"dist\\index.js","original":{"line":1,"column":509}},{"name":"e","generated":{"line":13,"column":36},"source":"dist\\index.js","original":{"line":1,"column":520}},{"generated":{"line":13,"column":37},"source":"dist\\index.js","original":{"line":1,"column":509}},{"generated":{"line":13,"column":39},"source":"dist\\index.js","original":{"line":1,"column":522}},{"generated":{"line":14,"column":0},"source":"dist\\index.js","original":{"line":1,"column":523}},{"name":"u","generated":{"line":14,"column":13},"source":"dist\\index.js","original":{"line":1,"column":530}},{"name":"p","generated":{"line":14,"column":15},"source":"dist\\index.js","original":{"line":1,"column":532}},{"name":"resolve","generated":{"line":14,"column":17},"source":"dist\\index.js","original":{"line":1,"column":534}},{"generated":{"line":14,"column":24},"source":"dist\\index.js","original":{"line":1,"column":532}},{"name":"e","generated":{"line":14,"column":25},"source":"dist\\index.js","original":{"line":1,"column":542}},{"generated":{"line":14,"column":26},"source":"dist\\index.js","original":{"line":1,"column":532}},{"generated":{"line":14,"column":27},"source":"dist\\index.js","original":{"line":1,"column":530}},{"generated":{"line":14,"column":28},"source":"dist\\index.js","original":{"line":1,"column":523}},{"generated":{"line":15,"column":0},"source":"dist\\index.js","original":{"line":1,"column":546}},{"generated":{"line":16,"column":0},"source":"dist\\index.js","original":{"line":1,"column":547}},{"name":"isParcelRequire","generated":{"line":16,"column":5},"source":"dist\\index.js","original":{"line":1,"column":549}},{"generated":{"line":16,"column":20},"source":"dist\\index.js","original":{"line":1,"column":547}},{"generated":{"line":16,"column":23},"source":"dist\\index.js","original":{"line":1,"column":565}},{"generated":{"line":16,"column":24},"source":"dist\\index.js","original":{"line":1,"column":566}},{"generated":{"line":16,"column":25},"source":"dist\\index.js","original":{"line":1,"column":547}},{"name":"u","generated":{"line":16,"column":27},"source":"dist\\index.js","original":{"line":1,"column":568}},{"name":"Module","generated":{"line":16,"column":29},"source":"dist\\index.js","original":{"line":1,"column":570}},{"generated":{"line":16,"column":35},"source":"dist\\index.js","original":{"line":1,"column":568}},{"generated":{"line":16,"column":38},"source":"dist\\index.js","original":{"line":1,"column":577}},{"name":"e","generated":{"line":16,"column":48},"source":"dist\\index.js","original":{"line":1,"column":586}},{"generated":{"line":16,"column":49},"source":"dist\\index.js","original":{"line":1,"column":577}},{"generated":{"line":16,"column":51},"source":"dist\\index.js","original":{"line":1,"column":588}},{"generated":{"line":17,"column":0},"source":"dist\\index.js","original":{"line":1,"column":589}},{"name":"id","generated":{"line":17,"column":9},"source":"dist\\index.js","original":{"line":1,"column":594}},{"generated":{"line":17,"column":11},"source":"dist\\index.js","original":{"line":1,"column":589}},{"name":"e","generated":{"line":17,"column":14},"source":"dist\\index.js","original":{"line":1,"column":597}},{"generated":{"line":17,"column":15},"source":"dist\\index.js","original":{"line":1,"column":589}},{"generated":{"line":17,"column":17},"source":"dist\\index.js","original":{"line":1,"column":599}},{"name":"bundle","generated":{"line":17,"column":22},"source":"dist\\index.js","original":{"line":1,"column":604}},{"generated":{"line":17,"column":28},"source":"dist\\index.js","original":{"line":1,"column":599}},{"name":"u","generated":{"line":17,"column":31},"source":"dist\\index.js","original":{"line":1,"column":611}},{"generated":{"line":17,"column":32},"source":"dist\\index.js","original":{"line":1,"column":589}},{"generated":{"line":17,"column":34},"source":"dist\\index.js","original":{"line":1,"column":613}},{"name":"exports","generated":{"line":17,"column":39},"source":"dist\\index.js","original":{"line":1,"column":618}},{"generated":{"line":17,"column":46},"source":"dist\\index.js","original":{"line":1,"column":613}},{"generated":{"line":17,"column":49},"source":"dist\\index.js","original":{"line":1,"column":626}},{"generated":{"line":17,"column":51},"source":"dist\\index.js","original":{"line":1,"column":589}},{"generated":{"line":18,"column":0},"source":"dist\\index.js","original":{"line":1,"column":629}},{"generated":{"line":18,"column":3},"source":"dist\\index.js","original":{"line":1,"column":547}},{"name":"u","generated":{"line":18,"column":5},"source":"dist\\index.js","original":{"line":1,"column":630}},{"name":"modules","generated":{"line":18,"column":7},"source":"dist\\index.js","original":{"line":1,"column":632}},{"generated":{"line":18,"column":14},"source":"dist\\index.js","original":{"line":1,"column":630}},{"name":"e","generated":{"line":18,"column":17},"source":"dist\\index.js","original":{"line":1,"column":640}},{"generated":{"line":18,"column":18},"source":"dist\\index.js","original":{"line":1,"column":547}},{"name":"u","generated":{"line":18,"column":20},"source":"dist\\index.js","original":{"line":1,"column":642}},{"name":"cache","generated":{"line":18,"column":22},"source":"dist\\index.js","original":{"line":1,"column":644}},{"generated":{"line":18,"column":27},"source":"dist\\index.js","original":{"line":1,"column":642}},{"name":"r","generated":{"line":18,"column":30},"source":"dist\\index.js","original":{"line":1,"column":650}},{"generated":{"line":18,"column":31},"source":"dist\\index.js","original":{"line":1,"column":547}},{"name":"u","generated":{"line":18,"column":33},"source":"dist\\index.js","original":{"line":1,"column":652}},{"name":"parent","generated":{"line":18,"column":35},"source":"dist\\index.js","original":{"line":1,"column":654}},{"generated":{"line":18,"column":41},"source":"dist\\index.js","original":{"line":1,"column":652}},{"name":"i","generated":{"line":18,"column":44},"source":"dist\\index.js","original":{"line":1,"column":661}},{"generated":{"line":18,"column":45},"source":"dist\\index.js","original":{"line":1,"column":547}},{"name":"u","generated":{"line":18,"column":47},"source":"dist\\index.js","original":{"line":1,"column":663}},{"name":"register","generated":{"line":18,"column":49},"source":"dist\\index.js","original":{"line":1,"column":665}},{"generated":{"line":18,"column":57},"source":"dist\\index.js","original":{"line":1,"column":663}},{"generated":{"line":18,"column":60},"source":"dist\\index.js","original":{"line":1,"column":674}},{"name":"r","generated":{"line":18,"column":70},"source":"dist\\index.js","original":{"line":1,"column":683}},{"generated":{"line":18,"column":71},"source":"dist\\index.js","original":{"line":1,"column":674}},{"name":"n","generated":{"line":18,"column":73},"source":"dist\\index.js","original":{"line":1,"column":685}},{"generated":{"line":18,"column":74},"source":"dist\\index.js","original":{"line":1,"column":674}},{"generated":{"line":18,"column":76},"source":"dist\\index.js","original":{"line":1,"column":687}},{"name":"e","generated":{"line":19,"column":0},"source":"dist\\index.js","original":{"line":1,"column":688}},{"name":"r","generated":{"line":19,"column":6},"source":"dist\\index.js","original":{"line":1,"column":690}},{"generated":{"line":19,"column":7},"source":"dist\\index.js","original":{"line":1,"column":688}},{"generated":{"line":19,"column":11},"source":"dist\\index.js","original":{"line":1,"column":693}},{"generated":{"line":19,"column":12},"source":"dist\\index.js","original":{"line":1,"column":694}},{"name":"e","generated":{"line":19,"column":22},"source":"dist\\index.js","original":{"line":1,"column":703}},{"generated":{"line":19,"column":23},"source":"dist\\index.js","original":{"line":1,"column":694}},{"name":"r","generated":{"line":19,"column":25},"source":"dist\\index.js","original":{"line":1,"column":705}},{"generated":{"line":19,"column":26},"source":"dist\\index.js","original":{"line":1,"column":694}},{"generated":{"line":19,"column":28},"source":"dist\\index.js","original":{"line":1,"column":707}},{"name":"r","generated":{"line":20,"column":0},"source":"dist\\index.js","original":{"line":1,"column":708}},{"name":"exports","generated":{"line":20,"column":8},"source":"dist\\index.js","original":{"line":1,"column":710}},{"generated":{"line":20,"column":15},"source":"dist\\index.js","original":{"line":1,"column":708}},{"name":"n","generated":{"line":20,"column":18},"source":"dist\\index.js","original":{"line":1,"column":718}},{"generated":{"line":20,"column":19},"source":"dist\\index.js","original":{"line":1,"column":708}},{"generated":{"line":21,"column":0},"source":"dist\\index.js","original":{"line":1,"column":720}},{"generated":{"line":21,"column":5},"source":"dist\\index.js","original":{"line":1,"column":693}},{"generated":{"line":21,"column":7},"source":"dist\\index.js","original":{"line":1,"column":721}},{"generated":{"line":21,"column":9},"source":"dist\\index.js","original":{"line":1,"column":693}},{"generated":{"line":21,"column":10},"source":"dist\\index.js","original":{"line":1,"column":688}},{"generated":{"line":22,"column":0},"source":"dist\\index.js","original":{"line":1,"column":725}},{"generated":{"line":22,"column":3},"source":"dist\\index.js","original":{"line":1,"column":547}},{"generated":{"line":22,"column":4},"source":"dist\\index.js","original":{"line":1,"column":726}},{"generated":{"line":22,"column":9},"source":"dist\\index.js","original":{"line":1,"column":730}},{"name":"f","generated":{"line":22,"column":13},"source":"dist\\index.js","original":{"line":1,"column":734}},{"generated":{"line":22,"column":17},"source":"dist\\index.js","original":{"line":1,"column":736}},{"generated":{"line":22,"column":18},"source":"dist\\index.js","original":{"line":1,"column":726}},{"name":"f","generated":{"line":22,"column":20},"source":"dist\\index.js","original":{"line":1,"column":738}},{"name":"n","generated":{"line":22,"column":24},"source":"dist\\index.js","original":{"line":1,"column":740}},{"name":"length","generated":{"line":22,"column":26},"source":"dist\\index.js","original":{"line":1,"column":742}},{"generated":{"line":22,"column":32},"source":"dist\\index.js","original":{"line":1,"column":726}},{"name":"f","generated":{"line":22,"column":34},"source":"dist\\index.js","original":{"line":1,"column":749}},{"generated":{"line":22,"column":37},"source":"dist\\index.js","original":{"line":1,"column":726}},{"name":"u","generated":{"line":23,"column":0},"source":"dist\\index.js","original":{"line":1,"column":753}},{"name":"n","generated":{"line":23,"column":6},"source":"dist\\index.js","original":{"line":1,"column":755}},{"name":"f","generated":{"line":23,"column":8},"source":"dist\\index.js","original":{"line":1,"column":757}},{"generated":{"line":23,"column":9},"source":"dist\\index.js","original":{"line":1,"column":755}},{"generated":{"line":23,"column":10},"source":"dist\\index.js","original":{"line":1,"column":753}},{"generated":{"line":24,"column":0},"source":"dist\\index.js","original":{"line":1,"column":726}},{"generated":{"line":24,"column":3},"source":"dist\\index.js","original":{"line":1,"column":761}},{"name":"n","generated":{"line":24,"column":7},"source":"dist\\index.js","original":{"line":1,"column":764}},{"name":"length","generated":{"line":24,"column":9},"source":"dist\\index.js","original":{"line":1,"column":766}},{"generated":{"line":24,"column":15},"source":"dist\\index.js","original":{"line":1,"column":761}},{"generated":{"line":24,"column":17},"source":"dist\\index.js","original":{"line":1,"column":773}},{"generated":{"line":25,"column":0},"source":"dist\\index.js","original":{"line":1,"column":774}},{"name":"c","generated":{"line":25,"column":8},"source":"dist\\index.js","original":{"line":1,"column":778}},{"name":"u","generated":{"line":25,"column":12},"source":"dist\\index.js","original":{"line":1,"column":780}},{"name":"n","generated":{"line":25,"column":14},"source":"dist\\index.js","original":{"line":1,"column":782}},{"name":"n","generated":{"line":25,"column":16},"source":"dist\\index.js","original":{"line":1,"column":784}},{"name":"length","generated":{"line":25,"column":18},"source":"dist\\index.js","original":{"line":1,"column":786}},{"generated":{"line":25,"column":24},"source":"dist\\index.js","original":{"line":1,"column":784}},{"generated":{"line":25,"column":27},"source":"dist\\index.js","original":{"line":1,"column":793}},{"generated":{"line":25,"column":28},"source":"dist\\index.js","original":{"line":1,"column":782}},{"generated":{"line":25,"column":29},"source":"dist\\index.js","original":{"line":1,"column":780}},{"generated":{"line":25,"column":30},"source":"dist\\index.js","original":{"line":1,"column":774}},{"generated":{"line":25,"column":31},"source":"dist\\index.js","original":{"line":1,"column":797}},{"name":"exports","generated":{"line":25,"column":51},"source":"dist\\index.js","original":{"line":1,"column":814}},{"generated":{"line":25,"column":58},"source":"dist\\index.js","original":{"line":1,"column":797}},{"name":"exports","generated":{"line":25,"column":99},"source":"dist\\index.js","original":{"line":1,"column":814}},{"generated":{"line":25,"column":106},"source":"dist\\index.js","original":{"line":1,"column":797}},{"generated":{"line":25,"column":112},"source":"dist\\index.js","original":{"line":1,"column":823}},{"generated":{"line":25,"column":127},"source":"dist\\index.js","original":{"line":1,"column":836}},{"name":"module","generated":{"line":25,"column":134},"source":"dist\\index.js","original":{"line":1,"column":843}},{"generated":{"line":25,"column":140},"source":"dist\\index.js","original":{"line":1,"column":797}},{"name":"module","generated":{"line":25,"column":143},"source":"dist\\index.js","original":{"line":1,"column":850}},{"name":"exports","generated":{"line":25,"column":150},"source":"dist\\index.js","original":{"line":1,"column":857}},{"generated":{"line":25,"column":157},"source":"dist\\index.js","original":{"line":1,"column":850}},{"name":"c","generated":{"line":25,"column":160},"source":"dist\\index.js","original":{"line":1,"column":865}},{"generated":{"line":25,"column":161},"source":"dist\\index.js","original":{"line":1,"column":797}},{"generated":{"line":25,"column":164},"source":"dist\\index.js","original":{"line":1,"column":867}},{"generated":{"line":25,"column":178},"source":"dist\\index.js","original":{"line":1,"column":879}},{"name":"define","generated":{"line":25,"column":185},"source":"dist\\index.js","original":{"line":1,"column":886}},{"generated":{"line":25,"column":191},"source":"dist\\index.js","original":{"line":1,"column":867}},{"name":"define","generated":{"line":25,"column":195},"source":"dist\\index.js","original":{"line":1,"column":894}},{"name":"amd","generated":{"line":25,"column":202},"source":"dist\\index.js","original":{"line":1,"column":901}},{"generated":{"line":25,"column":205},"source":"dist\\index.js","original":{"line":1,"column":867}},{"name":"define","generated":{"line":25,"column":208},"source":"dist\\index.js","original":{"line":1,"column":905}},{"generated":{"line":25,"column":215},"source":"dist\\index.js","original":{"line":1,"column":912}},{"generated":{"line":25,"column":227},"source":"dist\\index.js","original":{"line":1,"column":922}},{"generated":{"line":26,"column":0},"source":"dist\\index.js","original":{"line":1,"column":923}},{"name":"c","generated":{"line":26,"column":13},"source":"dist\\index.js","original":{"line":1,"column":930}},{"generated":{"line":26,"column":14},"source":"dist\\index.js","original":{"line":1,"column":923}},{"generated":{"line":27,"column":0},"source":"dist\\index.js","original":{"line":1,"column":932}},{"generated":{"line":27,"column":5},"source":"dist\\index.js","original":{"line":1,"column":905}},{"generated":{"line":27,"column":6},"source":"dist\\index.js","original":{"line":1,"column":867}},{"name":"t","generated":{"line":27,"column":9},"source":"dist\\index.js","original":{"line":1,"column":934}},{"generated":{"line":27,"column":15},"source":"dist\\index.js","original":{"line":1,"column":938}},{"name":"t","generated":{"line":27,"column":20},"source":"dist\\index.js","original":{"line":1,"column":943}},{"generated":{"line":27,"column":21},"source":"dist\\index.js","original":{"line":1,"column":938}},{"name":"c","generated":{"line":27,"column":25},"source":"dist\\index.js","original":{"line":1,"column":946}},{"generated":{"line":27,"column":26},"source":"dist\\index.js","original":{"line":1,"column":934}},{"generated":{"line":27,"column":27},"source":"dist\\index.js","original":{"line":1,"column":797}},{"generated":{"line":28,"column":0},"source":"dist\\index.js","original":{"line":1,"column":949}},{"name":"u","generated":{"line":28,"column":10},"source":"dist\\index.js","original":{"line":1,"column":956}},{"generated":{"line":28,"column":11},"source":"dist\\index.js","original":{"line":1,"column":949}},{"generated":{"line":29,"column":0},"source":"dist\\index.js","original":{"line":1,"column":958}},{"generated":{"line":29,"column":1},"source":"dist\\index.js","original":{"line":1,"column":14}},{"generated":{"line":29,"column":2},"source":"dist\\index.js","original":{"line":1,"column":959}},{"generated":{"line":29,"column":4},"source":"dist\\index.js","original":{"line":1,"column":960}},{"generated":{"line":29,"column":12},"source":"dist\\index.js","original":{"line":1,"column":967}},{"generated":{"line":29,"column":13},"source":"dist\\index.js","original":{"line":1,"column":968}},{"name":"require","generated":{"line":29,"column":23},"source":"dist\\index.js","original":{"line":1,"column":977}},{"generated":{"line":29,"column":30},"source":"dist\\index.js","original":{"line":1,"column":968}},{"name":"module","generated":{"line":29,"column":32},"source":"dist\\index.js","original":{"line":1,"column":985}},{"generated":{"line":29,"column":38},"source":"dist\\index.js","original":{"line":1,"column":968}},{"name":"exports","generated":{"line":29,"column":40},"source":"dist\\index.js","original":{"line":1,"column":992}},{"generated":{"line":29,"column":47},"source":"dist\\index.js","original":{"line":1,"column":968}},{"generated":{"line":29,"column":49},"source":"dist\\index.js","original":{"line":1,"column":1001}},{"generated":{"line":30,"column":0},"source":"dist\\index.js","original":{"line":2,"column":0}},{"generated":{"line":31,"column":0},"source":"dist\\index.js","original":{"line":2,"column":13}},{"name":"e","generated":{"line":31,"column":13},"source":"dist\\index.js","original":{"line":2,"column":22}},{"generated":{"line":31,"column":14},"source":"dist\\index.js","original":{"line":2,"column":13}},{"generated":{"line":31,"column":17},"source":"dist\\index.js","original":{"line":2,"column":25}},{"name":"console","generated":{"line":32,"column":0},"source":"dist\\index.js","original":{"line":2,"column":26}},{"name":"log","generated":{"line":32,"column":14},"source":"dist\\index.js","original":{"line":2,"column":34}},{"generated":{"line":32,"column":17},"source":"dist\\index.js","original":{"line":2,"column":26}},{"generated":{"line":32,"column":18},"source":"dist\\index.js","original":{"line":2,"column":38}},{"generated":{"line":32,"column":31},"source":"dist\\index.js","original":{"line":2,"column":26}},{"generated":{"line":33,"column":0},"source":"dist\\index.js","original":{"line":2,"column":53}},{"name":"defineProperty","generated":{"line":33,"column":12},"source":"dist\\index.js","original":{"line":2,"column":60}},{"generated":{"line":33,"column":26},"source":"dist\\index.js","original":{"line":2,"column":53}},{"name":"exports","generated":{"line":33,"column":27},"source":"dist\\index.js","original":{"line":2,"column":75}},{"generated":{"line":33,"column":34},"source":"dist\\index.js","original":{"line":2,"column":53}},{"generated":{"line":33,"column":36},"source":"dist\\index.js","original":{"line":2,"column":83}},{"generated":{"line":33,"column":48},"source":"dist\\index.js","original":{"line":2,"column":53}},{"generated":{"line":33,"column":50},"source":"dist\\index.js","original":{"line":2,"column":96}},{"name":"value","generated":{"line":33,"column":52},"source":"dist\\index.js","original":{"line":2,"column":97}},{"generated":{"line":33,"column":59},"source":"dist\\index.js","original":{"line":2,"column":103}},{"generated":{"line":33,"column":60},"source":"dist\\index.js","original":{"line":2,"column":104}},{"generated":{"line":33,"column":61},"source":"dist\\index.js","original":{"line":2,"column":96}},{"generated":{"line":33,"column":63},"source":"dist\\index.js","original":{"line":2,"column":53}},{"name":"exports","generated":{"line":33,"column":66},"source":"dist\\index.js","original":{"line":2,"column":108}},{"name":"doStuff","generated":{"line":33,"column":74},"source":"dist\\index.js","original":{"line":2,"column":116}},{"generated":{"line":33,"column":81},"source":"dist\\index.js","original":{"line":2,"column":108}},{"name":"e","generated":{"line":33,"column":84},"source":"dist\\index.js","original":{"line":2,"column":124}},{"generated":{"line":33,"column":85},"source":"dist\\index.js","original":{"line":2,"column":53}},{"generated":{"line":34,"column":0},"source":"dist\\index.js","original":{"line":3,"column":1}},{"generated":{"line":34,"column":3},"source":"dist\\index.js","original":{"line":1,"column":967}},{"generated":{"line":34,"column":5},"source":"dist\\index.js","original":{"line":3,"column":2}},{"generated":{"line":34,"column":7},"source":"dist\\index.js","original":{"line":1,"column":967}},{"generated":{"line":34,"column":8},"source":"dist\\index.js","original":{"line":1,"column":959}},{"generated":{"line":34,"column":10},"source":"dist\\index.js","original":{"line":3,"column":6}},{"generated":{"line":34,"column":18},"source":"dist\\index.js","original":{"line":3,"column":13}},{"generated":{"line":34,"column":19},"source":"dist\\index.js","original":{"line":3,"column":14}},{"name":"require","generated":{"line":34,"column":29},"source":"dist\\index.js","original":{"line":3,"column":23}},{"generated":{"line":34,"column":36},"source":"dist\\index.js","original":{"line":3,"column":14}},{"name":"module","generated":{"line":34,"column":38},"source":"dist\\index.js","original":{"line":3,"column":31}},{"generated":{"line":34,"column":44},"source":"dist\\index.js","original":{"line":3,"column":14}},{"name":"exports","generated":{"line":34,"column":46},"source":"dist\\index.js","original":{"line":3,"column":38}},{"generated":{"line":34,"column":53},"source":"dist\\index.js","original":{"line":3,"column":14}},{"generated":{"line":34,"column":55},"source":"dist\\index.js","original":{"line":3,"column":47}},{"generated":{"line":35,"column":0},"source":"dist\\index.js","original":{"line":4,"column":0}},{"generated":{"line":36,"column":0},"source":"dist\\index.js","original":{"line":4,"column":13}},{"name":"r","generated":{"line":36,"column":8},"source":"dist\\index.js","original":{"line":4,"column":17}},{"name":"require","generated":{"line":36,"column":12},"source":"dist\\index.js","original":{"line":4,"column":19}},{"generated":{"line":36,"column":20},"source":"dist\\index.js","original":{"line":4,"column":27}},{"generated":{"line":36,"column":29},"source":"dist\\index.js","original":{"line":4,"column":19}},{"generated":{"line":36,"column":30},"source":"dist\\index.js","original":{"line":4,"column":13}},{"generated":{"line":36,"column":31},"source":"dist\\index.js","original":{"line":4,"column":38}},{"generated":{"line":36,"column":32},"source":"dist\\index.js","original":{"line":4,"column":39}},{"name":"r","generated":{"line":36,"column":35},"source":"dist\\index.js","original":{"line":4,"column":41}},{"name":"doStuff","generated":{"line":36,"column":37},"source":"dist\\index.js","original":{"line":4,"column":43}},{"generated":{"line":36,"column":44},"source":"dist\\index.js","original":{"line":4,"column":38}},{"generated":{"line":37,"column":0},"source":"dist\\index.js","original":{"line":5,"column":1}},{"generated":{"line":37,"column":3},"source":"dist\\index.js","original":{"line":3,"column":13}},{"generated":{"line":37,"column":5},"source":"dist\\index.js","original":{"line":5,"column":2}},{"generated":{"line":37,"column":7},"source":"dist\\index.js","original":{"line":5,"column":3}},{"generated":{"line":37,"column":18},"source":"dist\\index.js","original":{"line":5,"column":13}},{"generated":{"line":37,"column":24},"source":"dist\\index.js","original":{"line":5,"column":2}},{"generated":{"line":37,"column":26},"source":"dist\\index.js","original":{"line":3,"column":13}},{"generated":{"line":37,"column":27},"source":"dist\\index.js","original":{"line":1,"column":959}},{"generated":{"line":37,"column":29},"source":"dist\\index.js","original":{"line":1,"column":14}},{"generated":{"line":37,"column":31},"source":"dist\\index.js","original":{"line":5,"column":23}},{"generated":{"line":37,"column":33},"source":"dist\\index.js","original":{"line":1,"column":14}},{"generated":{"line":37,"column":35},"source":"dist\\index.js","original":{"line":5,"column":26}},{"generated":{"line":37,"column":36},"source":"dist\\index.js","original":{"line":5,"column":27}},{"generated":{"line":37,"column":42},"source":"dist\\index.js","original":{"line":5,"column":26}},{"generated":{"line":37,"column":43},"source":"dist\\index.js","original":{"line":1,"column":14}},{"generated":{"line":37,"column":45},"source":"dist\\index.js","original":{"line":5,"column":36}},{"generated":{"line":37,"column":49},"source":"dist\\index.js","original":{"line":1,"column":14}},{"generated":{"line":37,"column":50},"source":"dist\\index.js","original":{"line":1,"column":0}},{"generated":{"line":38,"column":0},"source":"dist\\index.js","original":{"line":6,"column":0}}],"sources":{"dist\\index.js":"parcelRequire=function(e,r,n,t){var i=\"function\"==typeof parcelRequire&&parcelRequire,o=\"function\"==typeof require&&require;function u(n,t){if(!r[n]){if(!e[n]){var f=\"function\"==typeof parcelRequire&&parcelRequire;if(!t&&f)return f(n,!0);if(i)return i(n,!0);if(o&&\"string\"==typeof n)return o(n);var c=new Error(\"Cannot find module '\"+n+\"'\");throw c.code=\"MODULE_NOT_FOUND\",c}p.resolve=function(r){return e[n][1][r]||r};var l=r[n]=new u.Module(n);e[n][0].call(l.exports,p,l,l.exports,this)}return r[n].exports;function p(e){return u(p.resolve(e))}}u.isParcelRequire=!0,u.Module=function(e){this.id=e,this.bundle=u,this.exports={}},u.modules=e,u.cache=r,u.parent=i,u.register=function(r,n){e[r]=[function(e,r){r.exports=n},{}]};for(var f=0;f<n.length;f++)u(n[f]);if(n.length){var c=u(n[n.length-1]);\"object\"==typeof exports&&\"undefined\"!=typeof module?module.exports=c:\"function\"==typeof define&&define.amd?define(function(){return c}):t&&(this[t]=c)}return u}({\"1tFC\":[function(require,module,exports) {\n\"use strict\";function e(){console.log(\"Hello World\")}Object.defineProperty(exports,\"__esModule\",{value:!0}),exports.doStuff=e;\n},{}],\"Focm\":[function(require,module,exports) {\n\"use strict\";var r=require(\"./utils\");(0,r.doStuff)();\n},{\"./utils\":\"1tFC\"}]},{},[\"Focm\"], null)\n//# sourceMappingURL=/index.map"},"lineCount":null}},"hash":"6ba601f454aa1b9ddb9e4b229e1c28a0","cacheData":{"env":{}}}